{
  "edition": "6.0",
  "final": false,
  "components": [
    "DISCOVER-6.0",
    "GOVERNOR-1.2",
    "GUARDIAN-6.0",
    "HDFS-6.0",
    "HYPERBASE-6.0",
    "INCEPTOR-6.0",
    "KAFKA-6.0",
    "NOTEBOOK-6.0",
    "PILOT-1.2",
    "RUBIK-1.2",
    "SEARCH-6.0",
    "SLIPSTREAM-6.0",
    "SOPHON-2.0",
    "TERMINAL-1.2",
    "TRANSPORTER-1.2",
    "TXSQL-6.0",
    "WORKFLOW-1.2",
    "YARN-6.0"
  ],
  "templates": [
    {
      "level": "demo",
      "description": "演示模式",
      "description_en": "Demo mode"
    },
    {
      "level": "low",
      "description": "最佳性价比模式",
      "description_en": "Best price/performance model"
    },
    {
      "level": "medium",
      "description": "性能和性价比最佳配比模式",
      "description_en": "Performance and cost-effective matching model"
    },
    {
      "level": "high",
      "description": "最佳性能模式",
      "description_en": "Best performance model"
    }
  ],
  "is_distributed": true
}